Metadata-Version: 1.0
Name: innocuousbook-cli
Version: 1.0.0
Summary: Innocuous Book CLI
Home-page: UNKNOWN
Author: mao
Author-email: UNKNOWN
License: UNKNOWN
Keywords: innocuousbook
Platform: UNKNOWN
